LICENSE
MANIFEST.in
requirements.txt
setup.cfg
setup.py
test_requirements.txt
erc20_transfer_authorization/__init__.py
erc20_transfer_authorization/transfer_authorization.py
erc20_transfer_authorization.egg-info/PKG-INFO
erc20_transfer_authorization.egg-info/SOURCES.txt
erc20_transfer_authorization.egg-info/dependency_links.txt
erc20_transfer_authorization.egg-info/entry_points.txt
erc20_transfer_authorization.egg-info/requires.txt
erc20_transfer_authorization.egg-info/top_level.txt
erc20_transfer_authorization/data/ERC20TransferAuthorization.bin
erc20_transfer_authorization/data/ERC20TransferAuthorization.json
erc20_transfer_authorization/data/ERC20TransferAuthorization.metadata.json
erc20_transfer_authorization/runnable/publish.py
erc20_transfer_authorization/unittest/__init__.py
erc20_transfer_authorization/unittest/base.py